<?xml version="1.0" encoding="UTF-8"?>
<zabbix_export>
    <version>5.4</version>
    <date>2021-10-16T01:58:18Z</date>
    <groups>
        <group>
            <uuid>a571c0d144b14fd4a87a9d9b2aa9fcd6</uuid>
            <name>Templates/Applications</name>
        </group>
    </groups>
    <templates>
        <template>
            <uuid>142b8ee5547e4569b92814588b902085</uuid>
            <template>Template App Gov weather</template>
            <name>Template App Gov weather</name>
            <groups>
                <group>
                    <name>Templates/Applications</name>
                </group>
            </groups>
            <items>
                <item>
                    <uuid>a3930535926f4abf8f8deae4f4224688</uuid>
                    <name>Dewpoint</name>
                    <type>DEPENDENT</type>
                    <key>dewpoint</key>
                    <delay>0</delay>
                    <units>C</units>
                    <preprocessing>
                        <step>
                            <type>JSONPATH</type>
                            <parameters>
                                <parameter>$.properties.dewpoint.value</parameter>
                            </parameters>
                        </step>
                    </preprocessing>
                    <master_item>
                        <key>get_weather.http</key>
                    </master_item>
                    <request_method>POST</request_method>
                    <tags>
                        <tag>
                            <tag>Application</tag>
                            <value>GovWeather</value>
                        </tag>
                    </tags>
                </item>
                <item>
                    <uuid>a1b16c82463c486e92b22e88d4358ac8</uuid>
                    <name>Get Gov weather</name>
                    <type>HTTP_AGENT</type>
                    <key>get_weather.http</key>
                    <delay>10m</delay>
                    <history>1d</history>
                    <trends>0</trends>
                    <value_type>TEXT</value_type>
                    <timeout>10s</timeout>
                    <url>https://api.weather.gov/stations/{$STATION}/observations/latest</url>
                    <query_fields>
                        <query_field>
                            <name>require_qc</name>
                            <value>false</value>
                        </query_field>
                    </query_fields>
                    <status_codes>200-399</status_codes>
                    <headers>
                        <header>
                            <name>User-Agent</name>
                            <value>I am making a Zabbix plugin.Wanting to monitor weather data for several cities as a weather nerd. Thank you. MattIsam@yahoo.com</value>
                        </header>
                    </headers>
                    <tags>
                        <tag>
                            <tag>Application</tag>
                            <value>GovWeather</value>
                        </tag>
                    </tags>
                </item>
                <item>
                    <uuid>aae4c896540143c0b1c79a40321a42e9</uuid>
                    <name>Get weather HTTP response code</name>
                    <type>DEPENDENT</type>
                    <key>get_weathergov.http_code</key>
                    <delay>0</delay>
                    <history>7d</history>
                    <trends>0</trends>
                    <status>DISABLED</status>
                    <preprocessing>
                        <step>
                            <type>JSONPATH</type>
                            <parameters>
                                <parameter>$.body.cod</parameter>
                            </parameters>
                        </step>
                    </preprocessing>
                    <master_item>
                        <key>get_weather.http</key>
                    </master_item>
                    <request_method>POST</request_method>
                    <tags>
                        <tag>
                            <tag>Application</tag>
                            <value>GovWeather</value>
                        </tag>
                    </tags>
                    <triggers>
                        <trigger>
                            <uuid>410ef5ec59994a8398d98bb71a837606</uuid>
                            <expression>last(/Template App Gov weather/get_weathergov.http_code)&lt;&gt;200 or nodata(/Template App Gov weather/get_weathergov.http_code,30m)=1</expression>
                            <name>Issues with getting weather data</name>
                            <priority>WARNING</priority>
                            <manual_close>YES</manual_close>
                        </trigger>
                    </triggers>
                </item>
                <item>
                    <uuid>efa6f6aece7642ada779a0424365b4d4</uuid>
                    <name>GovWeather</name>
                    <type>DEPENDENT</type>
                    <key>govweather</key>
                    <delay>0</delay>
                    <trends>0</trends>
                    <status>DISABLED</status>
                    <value_type>CHAR</value_type>
                    <preprocessing>
                        <step>
                            <type>JSONPATH</type>
                            <parameters>
                                <parameter>$.body.weather[0].main</parameter>
                            </parameters>
                        </step>
                    </preprocessing>
                    <master_item>
                        <key>get_weather.http</key>
                    </master_item>
                    <request_method>POST</request_method>
                    <tags>
                        <tag>
                            <tag>Application</tag>
                            <value>GovWeather</value>
                        </tag>
                    </tags>
                </item>
                <item>
                    <uuid>0926df28a298466397fb7595193aa1a2</uuid>
                    <name>Humidity</name>
                    <type>DEPENDENT</type>
                    <key>humidity</key>
                    <delay>0</delay>
                    <value_type>FLOAT</value_type>
                    <units>%</units>
                    <preprocessing>
                        <step>
                            <type>JSONPATH</type>
                            <parameters>
                                <parameter>$.properties.relativeHumidity.value</parameter>
                            </parameters>
                        </step>
                    </preprocessing>
                    <master_item>
                        <key>get_weather.http</key>
                    </master_item>
                    <request_method>POST</request_method>
                    <tags>
                        <tag>
                            <tag>Application</tag>
                            <value>GovWeather</value>
                        </tag>
                    </tags>
                </item>
                <item>
                    <uuid>b9c0e62d7828489897dec8d39254243a</uuid>
                    <name>Weather Icon</name>
                    <type>DEPENDENT</type>
                    <key>icon</key>
                    <delay>0</delay>
                    <trends>0</trends>
                    <value_type>TEXT</value_type>
                    <preprocessing>
                        <step>
                            <type>JSONPATH</type>
                            <parameters>
                                <parameter>$.properties.icon</parameter>
                            </parameters>
                        </step>
                    </preprocessing>
                    <master_item>
                        <key>get_weather.http</key>
                    </master_item>
                    <tags>
                        <tag>
                            <tag>Application</tag>
                            <value>GovWeather</value>
                        </tag>
                    </tags>
                </item>
                <item>
                    <uuid>a9dacbc4d73b4b2c89769367dabeaa10</uuid>
                    <name>Pressure</name>
                    <type>DEPENDENT</type>
                    <key>pressure</key>
                    <delay>0</delay>
                    <value_type>FLOAT</value_type>
                    <units>Pa</units>
                    <preprocessing>
                        <step>
                            <type>JSONPATH</type>
                            <parameters>
                                <parameter>$.properties.barometricPressure.value</parameter>
                            </parameters>
                        </step>
                    </preprocessing>
                    <master_item>
                        <key>get_weather.http</key>
                    </master_item>
                    <tags>
                        <tag>
                            <tag>Application</tag>
                            <value>GovWeather</value>
                        </tag>
                    </tags>
                </item>
                <item>
                    <uuid>e3835630445648c7a296f47a40cbc392</uuid>
                    <name>Temperature</name>
                    <type>DEPENDENT</type>
                    <key>temperature.value</key>
                    <delay>0</delay>
                    <value_type>FLOAT</value_type>
                    <units>C</units>
                    <preprocessing>
                        <step>
                            <type>JSONPATH</type>
                            <parameters>
                                <parameter>$.properties.temperature.value</parameter>
                            </parameters>
                        </step>
                    </preprocessing>
                    <master_item>
                        <key>get_weather.http</key>
                    </master_item>
                    <request_method>POST</request_method>
                    <tags>
                        <tag>
                            <tag>Application</tag>
                            <value>GovWeather</value>
                        </tag>
                    </tags>
                </item>
                <item>
                    <uuid>da671a38008b4065a21aace61d22faec</uuid>
                    <name>High</name>
                    <type>DEPENDENT</type>
                    <key>temp_max</key>
                    <delay>0</delay>
                    <status>DISABLED</status>
                    <value_type>FLOAT</value_type>
                    <units>C</units>
                    <preprocessing>
                        <step>
                            <type>JSONPATH</type>
                            <parameters>
                                <parameter>$.body.main.temp_max</parameter>
                            </parameters>
                        </step>
                    </preprocessing>
                    <master_item>
                        <key>get_weather.http</key>
                    </master_item>
                    <tags>
                        <tag>
                            <tag>Application</tag>
                            <value>GovWeather</value>
                        </tag>
                    </tags>
                </item>
                <item>
                    <uuid>1ea435ad8d024d139b116f353df2d1ef</uuid>
                    <name>Low</name>
                    <type>DEPENDENT</type>
                    <key>temp_min</key>
                    <delay>0</delay>
                    <status>DISABLED</status>
                    <value_type>FLOAT</value_type>
                    <units>C</units>
                    <preprocessing>
                        <step>
                            <type>JSONPATH</type>
                            <parameters>
                                <parameter>$.body.main.temp_min</parameter>
                            </parameters>
                        </step>
                    </preprocessing>
                    <master_item>
                        <key>get_weather.http</key>
                    </master_item>
                    <tags>
                        <tag>
                            <tag>Application</tag>
                            <value>GovWeather</value>
                        </tag>
                    </tags>
                </item>
                <item>
                    <uuid>89d782de2dff446da1fa090ce1a19ef0</uuid>
                    <name>Visibility</name>
                    <type>DEPENDENT</type>
                    <key>visibility</key>
                    <delay>0</delay>
                    <value_type>FLOAT</value_type>
                    <units>m</units>
                    <preprocessing>
                        <step>
                            <type>JSONPATH</type>
                            <parameters>
                                <parameter>$.properties.visibility.value</parameter>
                            </parameters>
                        </step>
                    </preprocessing>
                    <master_item>
                        <key>get_weather.http</key>
                    </master_item>
                    <request_method>POST</request_method>
                    <tags>
                        <tag>
                            <tag>Application</tag>
                            <value>GovWeather</value>
                        </tag>
                    </tags>
                </item>
                <item>
                    <uuid>61366487fc0542859a840428ca0b116e</uuid>
                    <name>Weather description</name>
                    <type>DEPENDENT</type>
                    <key>weather.description</key>
                    <delay>0</delay>
                    <trends>0</trends>
                    <value_type>CHAR</value_type>
                    <preprocessing>
                        <step>
                            <type>JSONPATH</type>
                            <parameters>
                                <parameter>$.properties.textDescription</parameter>
                            </parameters>
                        </step>
                    </preprocessing>
                    <master_item>
                        <key>get_weather.http</key>
                    </master_item>
                    <request_method>POST</request_method>
                    <tags>
                        <tag>
                            <tag>Application</tag>
                            <value>GovWeather</value>
                        </tag>
                    </tags>
                </item>
                <item>
                    <uuid>b1a9650879314decab4014ddb0cf4969</uuid>
                    <name>Wind Direction</name>
                    <type>DEPENDENT</type>
                    <key>wind.deg</key>
                    <delay>0</delay>
                    <value_type>FLOAT</value_type>
                    <preprocessing>
                        <step>
                            <type>JSONPATH</type>
                            <parameters>
                                <parameter>$.properties.windDirection.value</parameter>
                            </parameters>
                        </step>
                    </preprocessing>
                    <master_item>
                        <key>get_weather.http</key>
                    </master_item>
                    <request_method>POST</request_method>
                    <tags>
                        <tag>
                            <tag>Application</tag>
                            <value>GovWeather</value>
                        </tag>
                    </tags>
                </item>
                <item>
                    <uuid>8dfd971b074b45f79f8c5c5ba6f150d1</uuid>
                    <name>Wind Speed</name>
                    <type>DEPENDENT</type>
                    <key>wind.speed</key>
                    <delay>0</delay>
                    <value_type>FLOAT</value_type>
                    <preprocessing>
                        <step>
                            <type>JSONPATH</type>
                            <parameters>
                                <parameter>$.properties.windSpeed.value</parameter>
                            </parameters>
                        </step>
                    </preprocessing>
                    <master_item>
                        <key>get_weather.http</key>
                    </master_item>
                    <tags>
                        <tag>
                            <tag>Application</tag>
                            <value>GovWeather</value>
                        </tag>
                    </tags>
                </item>
            </items>
            <macros>
                <macro>
                    <macro>{$STATION}</macro>
                    <value>KGCM</value>
                </macro>
            </macros>
        </template>
    </templates>
</zabbix_export>
